tt_badger/__init__.py
tt_badger/cli.py
tt_badger-0.1.2.dist-info/METADATA
tt_badger-0.1.2.dist-info/WHEEL
tt_badger-0.1.2.dist-info/entry_points.txt
tt_badger-0.1.2.dist-info/licenses/LICENSE
tt_badger-0.1.2.dist-info/RECORD
